LICENSE.md
MANIFEST.in
Makefile
README.md
setup.py
tox.ini
dpp_runner/VERSION
dpp_runner/__init__.py
dpp_runner/lib.py
dpp_runner/server.py
dpp_runner.egg-info/PKG-INFO
dpp_runner.egg-info/SOURCES.txt
dpp_runner.egg-info/dependency_links.txt
dpp_runner.egg-info/not-zip-safe
dpp_runner.egg-info/requires.txt
dpp_runner.egg-info/top_level.txt