Metadata-Version: 1.1
Name: dpp-runner
Version: 0.0.6
Summary: pipeline runner lib and server
Home-page: https://github.com/akariv/dpp-runner
Author: Adam Kariv
Author-email: adam.kariv@gmail.com
License: MIT
Keywords: data
Platform: UNKNOWN
Classifier: Development Status :: 4 - Beta
Classifier: Intended Audience :: Developers
Classifier: License :: OSI Approved :: MIT License
Classifier: Operating System :: OS Independent
Classifier: Programming Language :: Python :: 3.6
Classifier: Topic :: Software Development :: Libraries :: Python Modules
